orionis_cli/__init__.py
orionis_cli/api.py
orionis_cli/installer.py
orionis_cli/core/__init__.py
orionis_cli/core/manager.py
orionis_cli/core/setup.py
orionis_cli-0.282.0.dist-info/licenses/LICENCE
orionis_cli-0.282.0.dist-info/METADATA
orionis_cli-0.282.0.dist-info/WHEEL
orionis_cli-0.282.0.dist-info/entry_points.txt
orionis_cli-0.282.0.dist-info/top_level.txt
orionis_cli-0.282.0.dist-info/zip-safe
orionis_cli-0.282.0.dist-info/RECORD
